demucs_infer/__init__.py
demucs_infer/__main__.py
demucs_infer/api.py
demucs_infer/apply.py
demucs_infer/audio.py
demucs_infer/compat.py
demucs_infer/demucs.py
demucs_infer/hdemucs.py
demucs_infer/htdemucs.py
demucs_infer/log.py
demucs_infer/pretrained.py
demucs_infer/repo.py
demucs_infer/separate.py
demucs_infer/spec.py
demucs_infer/states.py
demucs_infer/transformer.py
demucs_infer/utils.py
demucs_infer/wdemucs.py
demucs_infer/remote/files.txt
demucs_infer/remote/hdemucs_mmi.yaml
demucs_infer/remote/htdemucs.yaml
demucs_infer/remote/htdemucs_6s.yaml
demucs_infer/remote/htdemucs_ft.yaml
demucs_infer/remote/mdx.yaml
demucs_infer/remote/mdx_extra.yaml
demucs_infer/remote/mdx_extra_q.yaml
demucs_infer/remote/mdx_q.yaml
demucs_infer/remote/repro_mdx_a.yaml
demucs_infer/remote/repro_mdx_a_hybrid_only.yaml
demucs_infer/remote/repro_mdx_a_time_only.yaml
demucs_infer-4.1.0.dist-info/METADATA
demucs_infer-4.1.0.dist-info/WHEEL
demucs_infer-4.1.0.dist-info/entry_points.txt
demucs_infer-4.1.0.dist-info/licenses/LICENSE
demucs_infer-4.1.0.dist-info/RECORD
