Metadata-Version: 2.4
Name: demucs-infer
Version: 4.1.0
Summary: Music source separation in the waveform domain - Inference-only (PyTorch 2.x)
Project-URL: Homepage, https://github.com/openmirlab/demucs-infer
Project-URL: Repository, https://github.com/openmirlab/demucs-infer
Project-URL: Original Demucs, https://github.com/facebookresearch/demucs
Project-URL: Bug Reports, https://github.com/openmirlab/demucs-infer/issues
Project-URL: Changelog, https://github.com/openmirlab/demucs-infer/blob/main/CHANGELOG.md
Author-email: Alexandre Défossez <defossez@fb.com>
Maintainer: worzpro Development Team
License: MIT
License-File: LICENSE
Keywords: audio,demucs,inference,music,source-separation
Classifier: Development Status :: 4 - Beta
Classifier: Intended Audience :: Developers
Classifier: Intended Audience :: Science/Research
Classifier: License :: OSI Approved :: MIT License
Classifier: Operating System :: OS Independent
Classifier: Programming Language :: Python :: 3
Classifier: Programming Language :: Python :: 3.8
Classifier: Programming Language :: Python :: 3.9
Classifier: Programming Language :: Python :: 3.10
Classifier: Programming Language :: Python :: 3.11
Classifier: Programming Language :: Python :: 3.12
Classifier: Topic :: Multimedia :: Sound/Audio
Classifier: Topic :: Scientific/Engineering :: Artificial Intelligence
Requires-Python: >=3.8
Requires-Dist: einops
Requires-Dist: julius>=0.2.3
Requires-Dist: openunmix
Requires-Dist: pyyaml
Requires-Dist: torch>=2.0.0
Requires-Dist: torchaudio>=2.0.0
Requires-Dist: tqdm
Provides-Extra: dev
Requires-Dist: black; extra == 'dev'
Requires-Dist: ruff; extra == 'dev'
Provides-Extra: mp3
Requires-Dist: lameenc>=1.2; extra == 'mp3'
Provides-Extra: quantized
Requires-Dist: diffq>=0.2.1; extra == 'quantized'
